{
   "absolute_quantity": null,
   "file_links": [],
   "labels": [],
   "mass_fraction": null,
   "material": {
      "id": "b33880eb-cf96-44b0-9f83-1d5e9d02c34a",
      "scope": "auto",
      "type": "link_by_uid"
   },
   "name": "Al in composition AAB16 with VAM in batch A Ingredient",
   "notes": null,
   "number_fraction": null,
   "process": {
      "id": "c81fb20a-b844-4b83-ac4e-953aedd35a70",
      "scope": "auto",
      "type": "link_by_uid"
   },
   "tags": [],
   "type": "ingredient_spec",
   "uids": {
      "auto": "ec54fe57-3664-4386-b4d0-818ad1d1b588"
   },
   "volume_fraction": null
}