{
   "absolute_quantity": null,
   "file_links": [],
   "labels": [],
   "mass_fraction": null,
   "material": {
      "id": "3a0949eb-71d3-4676-9f0c-9032ab4c13b1",
      "scope": "auto",
      "type": "link_by_uid"
   },
   "name": "Alloy (composition AAB14 with VAM in batch A) Ingredient",
   "notes": null,
   "number_fraction": null,
   "process": {
      "id": "4bece305-3fee-4f8f-8b84-82ddbd77fe94",
      "scope": "auto",
      "type": "link_by_uid"
   },
   "tags": [],
   "type": "ingredient_spec",
   "uids": {
      "auto": "9320f824-bfc9-44ca-affe-793bced14fa0"
   },
   "volume_fraction": null
}