{
   "absolute_quantity": null,
   "file_links": [],
   "labels": [],
   "mass_fraction": null,
   "material": {
      "id": "cb7ff114-7632-4211-8f8f-17c568dc2e74",
      "scope": "auto",
      "type": "link_by_uid"
   },
   "name": "Homogenized Alloy (composition AAB04 with VAM in batch A) Ingredient",
   "notes": null,
   "number_fraction": null,
   "process": {
      "id": "07bc688e-3bcd-42ba-b4e9-234d4763ab84",
      "scope": "auto",
      "type": "link_by_uid"
   },
   "spec": {
      "id": "9ed73efd-bf99-464a-ae82-2c85841676ff",
      "scope": "auto",
      "type": "link_by_uid"
   },
   "tags": [],
   "type": "ingredient_run",
   "uids": {
      "auto": "39f1ea7f-8a98-46f8-83a9-c4f79e3dafaf"
   },
   "volume_fraction": null
}