{
   "absolute_quantity": null,
   "file_links": [],
   "labels": [],
   "mass_fraction": null,
   "material": {
      "id": "dece958a-25ec-421a-9ec1-b236c69ae6c0",
      "scope": "auto",
      "type": "link_by_uid"
   },
   "name": "Al in composition AAB08 with VAM in batch A Ingredient",
   "notes": null,
   "number_fraction": null,
   "process": {
      "id": "c54b10a1-c117-4965-b8fc-adf2d8eebf1b",
      "scope": "auto",
      "type": "link_by_uid"
   },
   "spec": {
      "id": "53ea1cd5-4c0a-40fa-b559-54230c42f4f9",
      "scope": "auto",
      "type": "link_by_uid"
   },
   "tags": [],
   "type": "ingredient_run",
   "uids": {
      "auto": "f91a1c9d-50ab-46c9-b555-2722899a142b"
   },
   "volume_fraction": null
}