{
   "absolute_quantity": null,
   "file_links": [],
   "labels": [],
   "mass_fraction": null,
   "material": {
      "id": "a9a0dc73-2f00-43b3-86e7-9f6377cf8ddf",
      "scope": "auto",
      "type": "link_by_uid"
   },
   "name": "Co in composition AAB09 with VAM in batch A Ingredient",
   "notes": null,
   "number_fraction": null,
   "process": {
      "id": "30ca5a3b-e56b-4448-a4a8-388e6473c940",
      "scope": "auto",
      "type": "link_by_uid"
   },
   "spec": {
      "id": "b7b7a7e1-a8da-4c85-8e8a-83a74eab7d3c",
      "scope": "auto",
      "type": "link_by_uid"
   },
   "tags": [],
   "type": "ingredient_run",
   "uids": {
      "auto": "ab3cb8c7-3e3a-44d5-b059-4ced1d68bc7c"
   },
   "volume_fraction": null
}