{
   "absolute_quantity": null,
   "file_links": [],
   "labels": [],
   "mass_fraction": null,
   "material": {
      "id": "e65be69b-1782-4fc4-b1ec-ffab702569c2",
      "scope": "auto",
      "type": "link_by_uid"
   },
   "name": "Forged Alloy (composition AAB13 with VAM in batch A) Ingredient",
   "notes": null,
   "number_fraction": null,
   "process": {
      "id": "0ee84824-25d3-4da9-aab6-ef68c93070cd",
      "scope": "auto",
      "type": "link_by_uid"
   },
   "tags": [],
   "type": "ingredient_spec",
   "uids": {
      "auto": "e04a15ed-6ea2-4882-9336-4f18615bb507"
   },
   "volume_fraction": null
}