{
   "absolute_quantity": null,
   "file_links": [],
   "labels": [],
   "mass_fraction": null,
   "material": {
      "id": "c9dda662-a53a-4d74-86e0-4eaf1fd18a56",
      "scope": "auto",
      "type": "link_by_uid"
   },
   "name": "Alloy (composition AAB07 with VAM in batch A): Traveler Sample (XRD, T03) Ingredient",
   "notes": null,
   "number_fraction": null,
   "process": {
      "id": "bfa42dba-ac13-4444-90e8-bce19aa7a0a5",
      "scope": "auto",
      "type": "link_by_uid"
   },
   "spec": {
      "id": "25319150-8dc8-490a-8206-f8300d269740",
      "scope": "auto",
      "type": "link_by_uid"
   },
   "tags": [],
   "type": "ingredient_run",
   "uids": {
      "auto": "22abfde6-8aeb-4768-ade5-5b356d6a1a4e"
   },
   "volume_fraction": null
}