{
   "absolute_quantity": null,
   "file_links": [],
   "labels": [],
   "mass_fraction": null,
   "material": {
      "id": "aeb470a7-64e1-4467-9497-03a0fa98e54d",
      "scope": "auto",
      "type": "link_by_uid"
   },
   "name": "Forged Alloy (composition AAB14 with VAM in batch A) Ingredient",
   "notes": null,
   "number_fraction": null,
   "process": {
      "id": "aca917c4-15fb-45b2-88c5-450c52785f3b",
      "scope": "auto",
      "type": "link_by_uid"
   },
   "tags": [],
   "type": "ingredient_spec",
   "uids": {
      "auto": "ff0a0200-7757-42f9-a843-eb6996b5c27c"
   },
   "volume_fraction": null
}