{
   "absolute_quantity": null,
   "file_links": [],
   "labels": [],
   "mass_fraction": null,
   "material": {
      "id": "a428deb6-4221-4d65-b091-eebbacaadd87",
      "scope": "auto",
      "type": "link_by_uid"
   },
   "name": "composition AAB07 with VAM in batch A Ingredient",
   "notes": null,
   "number_fraction": null,
   "process": {
      "id": "0a98374a-af9e-4518-9c22-ae3a0d80def7",
      "scope": "auto",
      "type": "link_by_uid"
   },
   "spec": {
      "id": "bb84aa64-45c9-45f2-a076-1f235ec9e284",
      "scope": "auto",
      "type": "link_by_uid"
   },
   "tags": [],
   "type": "ingredient_run",
   "uids": {
      "auto": "c301c152-4c28-426b-9a58-46d73e66dc76"
   },
   "volume_fraction": null
}