{
   "file_links": [],
   "name": "Alloy (composition AAB02 with VAM in batch A): Traveler Sample (Tensile, T08)",
   "notes": null,
   "process": {
      "id": "2332798c-470b-4d09-8227-309c52d3de32",
      "scope": "auto",
      "type": "link_by_uid"
   },
   "properties": [],
   "tags": [],
   "template": {
      "id": "95bf5ad1-ce2e-4698-9674-fb90715a00e9",
      "scope": "auto",
      "type": "link_by_uid"
   },
   "type": "material_spec",
   "uids": {
      "auto": "877efbd3-233b-46ed-bf7b-3a53e8e6b4b9"
   }
}