{
   "conditions": [],
   "file_links": [],
   "material": {
      "id": "e33c3e40-957f-43e9-94c7-63571c16ed5a",
      "scope": "auto",
      "type": "link_by_uid"
   },
   "name": "Weighting V for composition AAB01 with VAM in batch A",
   "notes": null,
   "parameters": [],
   "properties": [
      {
         "file_links": [],
         "name": "Weighed Mass",
         "notes": null,
         "origin": "unknown",
         "template": {
            "id": "79a72be8-40fc-4757-b4bc-cb5f5eac5ccd",
            "scope": "auto",
            "type": "link_by_uid"
         },
         "type": "property",
         "value": {
            "nominal": 2.6805,
            "type": "nominal_real",
            "units": "gram"
         }
      },
      {
         "file_links": [],
         "name": "Mass Loss",
         "notes": null,
         "origin": "specified",
         "template": {
            "id": "921f0b4e-fa21-4b94-a61b-21b67968df5f",
            "scope": "auto",
            "type": "link_by_uid"
         },
         "type": "property",
         "value": {
            "nominal": 0.0,
            "type": "nominal_real",
            "units": "gram"
         }
      }
   ],
   "source": {
      "performed_by": "Wenle & Daniel",
      "performed_date": "2022-11-04",
      "type": "performed_source"
   },
   "spec": {
      "id": "916d740c-4971-495d-8ed8-b61921562497",
      "scope": "auto",
      "type": "link_by_uid"
   },
   "tags": [
      "composition_id::AAB01",
      "batch::A",
      "fabrication_method::VAM"
   ],
   "type": "measurement_run",
   "uids": {
      "auto": "12fabbb4-e9fb-447e-85fe-0835abc07e2c"
   }
}